MANIFEST.in
README.txt
setup.cfg
setup.py
collective/__init__.py
collective.contentlicensing.egg-info/PKG-INFO
collective.contentlicensing.egg-info/SOURCES.txt
collective.contentlicensing.egg-info/dependency_links.txt
collective.contentlicensing.egg-info/entry_points.txt
collective.contentlicensing.egg-info/namespace_packages.txt
collective.contentlicensing.egg-info/not-zip-safe
collective.contentlicensing.egg-info/requires.txt
collective.contentlicensing.egg-info/top_level.txt
collective/contentlicensing/INSTALL.txt
collective/contentlicensing/LICENSE.GPL
collective/contentlicensing/LICENSE.ZPL
collective/contentlicensing/LICENSE.txt
collective/contentlicensing/README.txt
collective/contentlicensing/__init__.py
collective/contentlicensing/config.py
collective/contentlicensing/configure.zcml
collective/contentlicensing/events.py
collective/contentlicensing/indexers.py
collective/contentlicensing/interfaces.py
collective/contentlicensing/rebuild_i18n.sh
collective/contentlicensing/setupHandlers.py
collective/contentlicensing/tool.gif
collective/contentlicensing/version.txt
collective/contentlicensing/DublinCoreExtensions/UpdateLicenseMetadata.py
collective/contentlicensing/DublinCoreExtensions/__init__.py
collective/contentlicensing/DublinCoreExtensions/configure.zcml
collective/contentlicensing/DublinCoreExtensions/interfaces.py
collective/contentlicensing/DublinCoreExtensions/patch.py
collective/contentlicensing/DublinCoreExtensions/terms.py
collective/contentlicensing/Extensions/Migration.py
collective/contentlicensing/Extensions/__init__.py
collective/contentlicensing/browser/RDFHeadViewlet.pt
collective/contentlicensing/browser/__init__.py
collective/contentlicensing/browser/ccwidget.pt
collective/contentlicensing/browser/ccwidget.py
collective/contentlicensing/browser/citation_view.pt
collective/contentlicensing/browser/configure.zcml
collective/contentlicensing/browser/contentlicensing.gif
collective/contentlicensing/browser/contentlicensingprefs.py
collective/contentlicensing/browser/copyright_byline.pt
collective/contentlicensing/browser/copyright_byline_viewlet.pt
collective/contentlicensing/browser/copyrightbyline.py
collective/contentlicensing/browser/dc_metadata.pt
collective/contentlicensing/browser/dcmetadata.py
collective/contentlicensing/browser/edit_fields_viewlet.pt
collective/contentlicensing/browser/insert_license.pt
