Metadata-Version: 1.0
Name: collective.contentlicensing
Version: 2.2.6
Summary: This tool is used to manage copyright licenses within plone.
Home-page: http://plone.org/products/contentlicensing
Author: enPraxis
Author-email: plone-developers@lists.sourceforge.net
License: GPL
Keywords: Licensing License Creative-Commons GPL All-Rights-Reserved Copyright Rights
Platform: UNKNOWN
Classifier: Framework :: Plone
Classifier: Programming Language :: Python
Classifier: Topic :: Software Development :: Libraries :: Python Modules
